persian_datepicker/__init__.py
persian_datepicker/persian_datepicker.py
persian_datepicker-1.5.5.dist-info/licenses/LICENSE
persian_datepicker-1.5.5.dist-info/METADATA
persian_datepicker-1.5.5.dist-info/WHEEL
persian_datepicker-1.5.5.dist-info/top_level.txt
persian_datepicker-1.5.5.dist-info/RECORD
