Metadata-Version: 2.4
Name: persian-datepicker
Version: 1.5.5
Summary: A Persian (Shamsi) DatePicker widget for Flet with animations, RTL support, and keyboard navigation.
Author-email: Ali Amini <aliamini9728@gmail.com>
License-Expression: MIT
Project-URL: Homepage, https://github.com/AliAminiCode/flet-persian-datepicker
Project-URL: Bug Tracker, https://github.com/AliAminiCode/flet-persian-datepicker/issues
Keywords: flet,persian,shamsi,datepicker,jalali,gui,persain datepicker,flet persain datepicker,persain datepicker flet
Classifier: Programming Language :: Python :: 3
Classifier: Operating System :: OS Independent
Classifier: Development Status :: 4 - Beta
Classifier: Intended Audience :: Developers
Classifier: Topic :: Software Development :: Libraries :: Python Modules
Requires-Python: >=3.7
License-File: LICENSE
Requires-Dist: flet>=0.19.0
Requires-Dist: jdatetime>=5.2.0
Dynamic: license-file
